{"small":[{"length":"small (<= 76)","text":""},{"length":"small (<= 76)","text":"\r\nAlways finish what you start especially if you're at a buffet.\r\n"},{"length":"small (<= 76)","text":"\r\nPatience is a virtue, unless you're at the DMV.\r\n"},{"length":"small (<= 76)","text":"\r\nMoney can't buy you happiness, but it can get you take out.\r\n"},{"length":"small (<= 76)","text":"\r\nWhen opportunity knocks make sure you don't have your head-phones on.\r\n"},{"length":"small (<= 76)","text":"\r\nNothing is impossible. Except Monday mornings.\r\n"},{"length":"small (<= 76)","text":"\r\nYou are not illiterate.\r\n"},{"length":"small (<= 76)","text":"\r\nIf you don’t fight for what you want, don’t cry for what you lost.\r\n"},{"length":"small (<= 76)","text":"\r\nA comfort zone is a magical place where nothing ever grows.\r\n"},{"length":"small (<= 76)","text":"\r\nGive yourself a break before you breakdown.\r\n"},{"length":"small (<= 76)","text":"\r\nInspiration within is waiting for you. It's time to go deep.\r\n"},{"length":"small (<= 76)","text":"\r\nImagine your ideals, then make them real.\r\n"},{"length":"small (<= 76)","text":"\r\nIdeas you believe are absurd ultimately lead to success!\r\n"},{"length":"small (<= 76)","text":"\r\nIf a man has common sense, he has all the sense there is.\r\n"},{"length":"small (<= 76)","text":"\r\nIf a true sense of value is to be yours it must come through service.\r\n"},{"length":"small (<= 76)","text":"\r\nIf absolute can be defined, then absolute is not absolute anymore.\r\n"},{"length":"small (<= 76)","text":"\r\nHappiness is enjoying what you got. Never from what you want.\r\n"},{"length":"small (<= 76)","text":"\r\nHappiness is not a reward, it's a consequence.\r\n"},{"length":"small (<= 76)","text":"\r\nGo confidently in the direction of your dreams.\r\n"},{"length":"small (<= 76)","text":"\r\nGo take a rest; you deserve it.\r\n"},{"length":"small (<= 76)","text":"\r\nGenius is eternal patience.\r\n"},{"length":"small (<= 76)","text":"\r\nFollow the advice of your heart.\r\n"},{"length":"small (<= 76)","text":"\r\nFollow the middle path. Neither extreme will make you happy.\r\n"},{"length":"small (<= 76)","text":"\r\nTake your time today so you won't walk in mud.\r\n"},{"length":"small (<= 76)","text":"\r\nFight for it. You will come out on the top.\r\n"},{"length":"small (<= 76)","text":"\r\nFinancial hardship in your life is coming to an end!\r\n"},{"length":"small (<= 76)","text":"\r\nFailure is the tuition you pay for success.\r\n"},{"length":"small (<= 76)","text":"\r\nExpect a change for the better.\r\n"},{"length":"small (<= 76)","text":"\r\nExpect great things, and great things will come.\r\n"},{"length":"small (<= 76)","text":"\r\nExamine the situation before you act impulsively.\r\n"},{"length":"small (<= 76)","text":"\r\nEat, drink and be merry, for tomorrow you may diet.\r\n"},{"length":"small (<= 76)","text":"\r\nDon't repay a kindness, pass it on.\r\n"},{"length":"small (<= 76)","text":"\r\nDon't put all your eggs in one basket.\r\n"},{"length":"small (<= 76)","text":"\r\nDon't scrap everything! See what you can salvage.\r\n"},{"length":"small (<= 76)","text":"\r\nDon't fret. All your friends will be able to zig whenever you zag.\r\n"},{"length":"small (<= 76)","text":"\r\nCreative energy is up - capitalize on it.\r\n"},{"length":"small (<= 76)","text":"\r\nCuriosity kills boredom. Nothing can kill curiosity.\r\n"},{"length":"small (<= 76)","text":"\r\nCommon sense is instinct.  Enough of it is genius.\r\n"},{"length":"small (<= 76)","text":"\r\nCall an old friend today.\r\n"},{"length":"small (<= 76)","text":"\r\nBuy things because you need them, not because they are on sale.\r\n"},{"length":"small (<= 76)","text":"\r\nBetter ask twice than lose yourself once.\r\n"},{"length":"small (<= 76)","text":"\r\nBehavior is a mirror in which everyone shows his own image.\r\n"},{"length":"small (<= 76)","text":"\r\nBelieve in your abilities, confidence will lead you on.\r\n"},{"length":"small (<= 76)","text":"\r\nBalance life with a little sweet & sour.\r\n"},{"length":"small (<= 76)","text":"\r\nAsk advice, but use your own common sense.\r\n"},{"length":"small (<= 76)","text":"\r\nAsk yourself this question: \\\"Is my attitude worth catching?\\\"\r\n"},{"length":"small (<= 76)","text":"\r\nAttitude is a little thing that makes a BIG difference.\r\n"},{"length":"small (<= 76)","text":"\r\nAn unexpected check or fortune will arrive today.\r\n"},{"length":"small (<= 76)","text":"\r\nAn unexpected event will bring you riches.\r\n"},{"length":"small (<= 76)","text":"\r\nAn upset is an opportunity to see the truth.\r\n"},{"length":"small (<= 76)","text":"\r\nAny job, big or small; do it right, or not at all.\r\n"},{"length":"small (<= 76)","text":"\r\nAny rough times are behind you.\r\n"},{"length":"small (<= 76)","text":"\r\nAnyone can memorize things, but the important thing is to understand.\r\n"},{"length":"small (<= 76)","text":"\r\nAn important person will offer you support.\r\n"},{"length":"small (<= 76)","text":"\r\nAn investment in knowledge always pays the best interest.\r\n"},{"length":"small (<= 76)","text":"\r\nAn investment in yourself will pay dividends for the rest of your life.\r\n"},{"length":"small (<= 76)","text":"\r\nAn old wish will come true.\r\n"},{"length":"small (<= 76)","text":"\r\nAlthough it feels like a roller coaster now, life will calm down.\r\n"},{"length":"small (<= 76)","text":"\r\nAll your hard work will soon pay off.\r\n"},{"length":"small (<= 76)","text":"\r\nAll your sorrows will vanish.\r\n"},{"length":"small (<= 76)","text":"\r\nAll the little things will add to a happy journey.\r\n"},{"length":"small (<= 76)","text":"\r\nAll that we are is a result of what we have thought.\r\n"},{"length":"small (<= 76)","text":"\r\nAll the answers you need are right there in front of you!\r\n"},{"length":"small (<= 76)","text":"\r\nAll the effort you are making will ultimately pay off.\r\n"},{"length":"small (<= 76)","text":"\r\nAct boldly and unseen forces will come to your aid.\r\n"},{"length":"small (<= 76)","text":""}],"medium":[{"length":"medium (> 76 && <= 114)","text":"\r\nAlways look ahead to reach your goals, only look down when you have stepped on something along the way.\r\n"},{"length":"medium (> 76 && <= 114)","text":"\r\nAlways go the extra mile, because you don't know if the next one has dim sum.\r\n"},{"length":"medium (> 76 && <= 114)","text":"\r\nIf you bite the hand that feeds you, it won't taste as good as the food you were fed.\r\n"},{"length":"medium (> 76 && <= 114)","text":"\r\nEverything you are against weakens you. Everything you are for empowers you.\r\n"},{"length":"medium (> 76 && <= 114)","text":"\r\nDon't get so caught up in the daily grind that you never find any time to enjoy yourself.\r\n"},{"length":"medium (> 76 && <= 114)","text":"\r\nBusiness is a lot like playing tennis; if you don't serve well, you lose.\r\n"},{"length":"medium (> 76 && <= 114)","text":"\r\nBefore you wonder \\\"Am I doing things right,\\\" ask \\\"Am I doing the right things?\\\"\r\n"}],"large":[]}